latticeflow/__init__.py
latticeflow/info.py
latticeflow-0.0.1.dist-info/METADATA
latticeflow-0.0.1.dist-info/WHEEL
latticeflow-0.0.1.dist-info/top_level.txt
latticeflow-0.0.1.dist-info/RECORD
